eipspy/__init__.py
eipspy-0.1.0b1.dist-info/licenses/LICENSE
eipspy-0.1.0b1.dist-info/METADATA
eipspy-0.1.0b1.dist-info/WHEEL
eipspy-0.1.0b1.dist-info/top_level.txt
eipspy-0.1.0b1.dist-info/RECORD
