Metadata-Version: 2.4
Name: eipspy
Version: 0.1.0b1
Summary: Elite India PowerScript for Python - A comprehensive AI/ML framework designed to simplify and accelerate artificial intelligence development
Author-email: EIPSPy Team <eipspy@eliteindia.org>
Maintainer-email: EIPSPy Team <eipspy@eliteindia.org>
License: MIT
Project-URL: Homepage, https://github.com/SaleemLww/EIPSPy
Project-URL: Documentation, https://github.com/SaleemLww/EIPSPy#readme
Project-URL: Repository, https://github.com/SaleemLww/EIPSPy
Project-URL: Issues, https://github.com/SaleemLww/EIPSPy/issues
Project-URL: Changelog, https://github.com/SaleemLww/EIPSPy/blob/main/eipspy-pypi/CHANGELOG.md
Keywords: agi,artificial-intelligence,machine-learning,neural-networks,quantum-computing
Classifier: Development Status :: 1 - Planning
Classifier: Intended Audience :: Developers
Classifier: Intended Audience :: Science/Research
Classifier: License :: OSI Approved :: MIT License
Classifier: Operating System :: OS Independent
Classifier: Programming Language :: Python :: 3
Classifier: Programming Language :: Python :: 3.8
Classifier: Programming Language :: Python :: 3.9
Classifier: Programming Language :: Python :: 3.10
Classifier: Programming Language :: Python :: 3.11
Classifier: Programming Language :: Python :: 3.12
Classifier: Programming Language :: Python :: 3.13
Classifier: Topic :: Scientific/Engineering :: Artificial Intelligence
Classifier: Topic :: Software Development :: Libraries :: Python Modules
Requires-Python: >=3.8
License-File: LICENSE
Dynamic: license-file
